arduinoserial2/__init__.py
arduinoserial2/arduinoserial2.py
arduinoserial2-1.0.2.dist-info/LICENSE
arduinoserial2-1.0.2.dist-info/METADATA
arduinoserial2-1.0.2.dist-info/WHEEL
arduinoserial2-1.0.2.dist-info/entry_points.txt
arduinoserial2-1.0.2.dist-info/top_level.txt
arduinoserial2-1.0.2.dist-info/RECORD
