Metadata-Version: 2.1
Name: arduinoserial2
Version: 1.0.2
Summary: ArduinoSerial2: Connects Arudino with Computer 
Home-page: https://github.com/gokul6350/ArduinoSerial2
Author: SK Gokulbarath
Author-email: gokul00060@gmail.com
License: UNKNOWN
Platform: UNKNOWN
Classifier: License :: OSI Approved :: MIT License
Classifier: Programming Language :: Python :: 3
Classifier: Programming Language :: Python :: 3.6
Classifier: Programming Language :: Python :: 3.7
Classifier: Programming Language :: Python :: 3.8
Classifier: Programming Language :: Python :: 3.9
License-File: LICENSE
Requires-Dist: pyserial
